_pylibkriging.cpython-38-darwin.so
libarmadillo.15.0.1.dylib
libarmadillo.15.dylib
libarmadillo.dylib
pylibkriging/__init__.py
pylibkriging/__main__.py
pylibkriging-0.9.2.dist-info/LICENSE
pylibkriging-0.9.2.dist-info/METADATA
pylibkriging-0.9.2.dist-info/WHEEL
pylibkriging-0.9.2.dist-info/top_level.txt
pylibkriging-0.9.2.dist-info/RECORD
