Metadata-Version: 2.1
Name: pylibkriging
Version: 0.9.2
Summary: Python binding for LibKriging
Home-page: https://github.com/libKriging/libKriging
Author: Pascal Havé
Author-email: hpwxf@haveneer.com
License: UNKNOWN
Platform: UNKNOWN
Requires-Python: >=3.7
Requires-Dist: numpy<2,>=1.18
